Metadata-Version: 2.1
Name: trabajojh
Version: 0.1
Summary: Trabajo en clases
Author: jheomarasollesgarcia
Author-email: jheomaras@gmail.com
License: MIT
